README.rst
setup.py
BioSignalML.egg-info/PKG-INFO
BioSignalML.egg-info/SOURCES.txt
BioSignalML.egg-info/dependency_links.txt
BioSignalML.egg-info/requires.txt
BioSignalML.egg-info/top_level.txt
BioSignalML.egg-info/zip-safe
biosignalml/__init__.py
biosignalml/x.py
biosignalml/client/__init__.py
biosignalml/client/repository.py
biosignalml/data/__init__.py
biosignalml/data/convert.py
biosignalml/data/time.py
biosignalml/formats/__init__.py
biosignalml/formats/edf/__init__.py
biosignalml/formats/edf/annotate.py
biosignalml/formats/edf/edffile.py
biosignalml/formats/hdf5/__init__.py
biosignalml/formats/hdf5/h5recording.py
biosignalml/formats/raw/__init__.py
biosignalml/formats/wfdb/__init__.py
biosignalml/model/__init__.py
biosignalml/model/annotation.py
biosignalml/model/core.py
biosignalml/model/event.py
biosignalml/model/mapping.py
biosignalml/model/ontology.py
biosignalml/model/recording.py
biosignalml/model/segment.py
biosignalml/model/signal.py
biosignalml/rdf/__init__.py
biosignalml/rdf/sparqlstore.py
biosignalml/repository/__init__.py
biosignalml/repository/graphstore.py
biosignalml/transports/__init__.py
biosignalml/transports/stream.py
biosignalml/units/__init__.py
biosignalml/units/convert.py
biosignalml/units/ontology.py
biosignalml/utils/__init__.py