Metadata-Version: 1.1
Name: BioSignalML
Version: 0.5.0
Summary: Python BioSignal Abstraction Library
Home-page: https://github.com/dbrnz/biosignalml-corelib
Author: David Brooks
Author-email: d.brooks@auckland.ac.nz
License: ASL
Platform: UNKNOWN
Classifier: Development Status :: 4 - Beta
Classifier: Environment :: Console
Classifier: Environment :: Web Environment
Classifier: Intended Audience :: Science/Research
Classifier: Intended Audience :: Developers
Classifier: License :: OSI Approved :: Apache Software License
Classifier: Operating System :: MacOS :: MacOS X
Classifier: Operating System :: Microsoft :: Windows
Classifier: Operating System :: POSIX
Classifier: Programming Language :: Python
Classifier: Topic :: Scientific/Engineering :: Bio-Informatics
Provides: biosignalml
